nonebot_plugin_eop_ai/__init__.py
nonebot_plugin_eop_ai/config.py
nonebot_plugin_eop_ai/matchers.py
nonebot_plugin_eop_ai/rules.py
nonebot_plugin_eop_ai/utils.py
nonebot_plugin_eop_ai-0.3.5.dist-info/METADATA
nonebot_plugin_eop_ai-0.3.5.dist-info/WHEEL
nonebot_plugin_eop_ai-0.3.5.dist-info/RECORD
