Metadata-Version: 2.3
Name: nonebot_plugin_eop_ai
Version: 0.3.5
Summary: Nonebot2 一款调用eop api的AI聊天插件
License: MIT
Author: nikissXI
Author-email: 1299577815@qq.com
Requires-Python: >=3.8
Classifier: License :: OSI Approved :: MIT License
Classifier: Programming Language :: Python :: 3
Classifier: Programming Language :: Python :: 3.8
Classifier: Programming Language :: Python :: 3.9
Classifier: Programming Language :: Python :: 3.10
Classifier: Programming Language :: Python :: 3.11
Classifier: Programming Language :: Python :: 3.12
Classifier: Programming Language :: Python :: 3.13
Requires-Dist: aiohttp (>=3.11.0)
Requires-Dist: mdx-breakless-lists (>=1.0.1)
Requires-Dist: mdx-truly-sane-lists (>=1.3)
Requires-Dist: nonebot-adapter-onebot (>=2.0.0)
Requires-Dist: nonebot-plugin-htmlrender (>=0.2.1)
Requires-Dist: nonebot2 (>=2.0.0rc1)
Project-URL: Documentation, https://github.com/nikissXI/nonebot_plugins/tree/main/nonebot_plugin_eop_ai#README.md
Project-URL: Homepage, https://github.com/nikissXI/nonebot_plugins/tree/main/nonebot_plugin_eop_ai
Project-URL: Repository, https://github.com/nikissXI/nonebot_plugins/tree/main/nonebot_plugin_eop_ai
